{
  "generated": true,
  "code": "🦵🏼",
  "Unicode": [
    "U+1F9BF",
    "U+1F3FD"
  ],
  "slug": "leg-medium-light-skin-tone",
  "shortcodes": {
    "github": ":leg_medium_light_skin_tone:",
    "slack": ":leg_medium_light_skin_tone:",
    "discord": ":leg_medium_light_skin_tone:"
  },
  "title": "Leg Medium Light Skin Tone",
  "keywords": [
    "leg",
    "limb",
    "walking",
    "movement",
    "medium light skin tone",
    "prosthetic"
  ],
  "category": "People & Body",
  "alsoKnownAs": [
    "Leg Medium Light"
  ],
  "version": {
    "unicode-version": "13.1",
    "emoji-version": "13.1"
  },
  "description": "Depicts a leg, often used to represent movement, walking, or physical action. The medium-light skin tone specifies the individual. Can also refer to prosthetics.",
  "apple_vendor_description": "The leg emoji with a medium-light skin tone on Apple devices is rendered with Apple's signature realistic lighting and soft, rounded form, giving it a smooth and lifelike appearance. The subtle shading and gentle curve of the calf suggest natural movement and presence, making it feel tangible. This emoji on Apple devices is commonly used to indicate walking, running, or simply being present and active in a situation."
}