{
  "generated": true,
  "code": "🫶🏼",
  "Unicode": [
    "U+1F90D",
    "U+1F3FC"
  ],
  "slug": "heart-hands-medium-light-skin-tone",
  "shortcodes": {
    "github": ":heart_hands_medium_light_skin_tone:",
    "slack": ":heart_hands_medium_light_skin_tone:",
    "discord": ":heart_hands_medium_light_skin_tone:"
  },
  "title": "Heart Hands Medium Light Skin Tone",
  "keywords": [
    "heart",
    "hands",
    "love",
    "affection",
    "gratitude",
    "support",
    "medium light skin tone"
  ],
  "category": "People & Body",
  "alsoKnownAs": [
    "Heart Hands",
    "Medium Light Skin Tone Heart Hands"
  ],
  "version": {
    "unicode-version": "14.0",
    "emoji-version": "13.1"
  },
  "description": "Two hands forming a heart shape, with a medium-light skin tone. This emoji expresses love, affection, support, and gratitude.",
  "apple_vendor_description": "On Apple devices, the heart hands emoji showcases two hands coming together to form a heart shape, rendered with a soft, medium-light skin tone. Apple's signature glossy 3D shading and realistic lighting give these hands a gentle, rounded appearance, conveying warmth and affection. This emoji is a beautiful visual metaphor for love, care, and emotional connection, often used to express deep feelings on Apple devices."
}