{
  "generated": true,
  "code": "🧛🏽",
  "Unicode": [
    "U+1F9DB",
    "U+1F3FD"
  ],
  "slug": "vampire-medium-dark-skin-tone",
  "shortcodes": {
    "github": ":vampire_medium_dark_skin_tone:",
    "slack": ":vampire_medium_dark_skin_tone:",
    "discord": ":vampire_medium_dark_skin_tone:"
  },
  "title": "Vampire Medium Dark Skin Tone",
  "keywords": [
    "vampire",
    "medium dark skin",
    "halloween",
    "mythical",
    "creature"
  ],
  "category": "People & Body",
  "alsoKnownAs": [
    "Dracula",
    "Medium Dark Vampire"
  ],
  "version": {
    "unicode-version": "10.0",
    "emoji-version": "7.0"
  },
  "description": "A person dressed as a vampire with medium-dark skin tone, often depicted with fangs, a cape, and a pale complexion. It can represent Halloween, gothic themes, or mythical creatures.",
  "apple_vendor_description": "On Apple devices, this vampire emoji embodies a chilling elegance with its medium-dark skin tone rendered in Apple's signature glossy 3D style.  Its sharp, captivating eyes and subtle, confident smirk suggest a timeless mystique, while the soft, rounded edges of its hair and cape add a touch of refined detail.  This emoji on Apple devices is perfect for conveying a sense of playful intrigue, dark humor, or a touch of the supernatural in your digital conversations."
}