{
  "generated": true,
  "code": "🧑‍❤️‍👨",
  "Unicode": [
    "U+1F9D1",
    "U+200D",
    "U+2764",
    "U+FE0F",
    "U+200D",
    "U+1F48B",
    "U+200D",
    "U+1F468"
  ],
  "slug": "couple-with-heart-person-man-medium-light-skin-tone-no-skin-tone",
  "shortcodes": {
    "github": ":couple_with_heart_person_man:",
    "slack": ":couple_with_heart_person_man:",
    "discord": ":couple_with_heart_person_man:"
  },
  "title": "Couple With Heart Person Man Medium Light Skin Tone No Skin Tone",
  "keywords": [
    "couple",
    "love",
    "romance",
    "relationship",
    "heart",
    "man",
    "person"
  ],
  "category": "People & Body",
  "alsoKnownAs": [
    "Couple With Heart (Person, Man)"
  ],
  "version": {
    "unicode-version": "13.0",
    "emoji-version": "1.0"
  },
  "description": "Represents romantic love between a person and a man, often signifying a strong, affectionate bond or a couple celebrating their relationship.",
  "apple_vendor_description": "On Apple devices, this emoji depicts a tender embrace between two figures, with the left figure showcasing a medium-light skin tone and the right having a neutral, uncolored hue, symbolizing a universal representation of connection. A vibrant, heart-shaped glow emanates from their joined forms, rendered with Apple’s signature glossy 3D shading and smooth gradients for a soft, inviting feel. The figures are subtly angled towards each other, their forms outlined with gentle, rounded edges that convey a sense of closeness and affection, making it ideal for expressing romantic love or deep platonic bonds in digital communication."
}