{
  "generated": true,
  "code": "👩‍🦽‍➡️",
  "Unicode": [
    "U+1F469",
    "U+200D",
    "U+1F9BD",
    "U+200D",
    "U+27A1",
    "U+FE0F"
  ],
  "slug": "woman-in-manual-wheelchair-facing-right",
  "shortcodes": {
    "github": ":woman_in_manual_wheelchair_facing_right:",
    "slack": ":woman_in_manual_wheelchair_facing_right:",
    "discord": ":woman_in_manual_wheelchair_facing_right:"
  },
  "title": "Woman in Manual Wheelchair Facing Right",
  "keywords": [
    "accessibility",
    "wheelchair",
    "woman",
    "manual wheelchair",
    "mobility",
    "disability",
    "independence"
  ],
  "senses": {
    "adjectives": [
      "Used to represent independence, mobility, or accessibility."
    ],
    "verbs": [
      "Depicts the act of moving or navigating using a manual wheelchair."
    ],
    "nouns": [
      "A woman seated in a manual wheelchair, facing right."
    ]
  },
  "category": "People & Body",
  "alsoKnownAs": [
    "Woman Using Manual Wheelchair",
    "Woman in Wheelchair Facing Right"
  ],
  "version": {
    "unicode-version": "15.1",
    "emoji-version": "15.1"
  },
  "description": "A woman shown sitting in a manual wheelchair and facing toward the right. Represents accessibility, independence, or mobility support. Can also be used in discussions about disability inclusion or movement.",
  "apple_vendor_description": "On Apple devices, the woman in manual wheelchair facing right emoji depicts a female figure seated in a wheelchair, rendered with realistic body proportions and soft, rounded gradients. The metal frame and wheels show subtle shading, emphasizing Apple’s detailed design style. It symbolizes independence, accessibility, and inclusive representation for people using mobility aids."
}
