{
  "generated": true,
  "code": "🤏Dark",
  "Unicode": [
    "U+1F90C",
    "U+1F3FE"
  ],
  "slug": "pinching-hand-medium-dark-skin-tone",
  "shortcodes": {
    "github": ":pinching_hand_medium_dark_skin_tone:",
    "slack": ":pinching_hand_medium_dark_skin_tone:",
    "discord": ":pinching_hand_medium_dark_skin_tone:"
  },
  "title": "Pinching Hand Medium Dark Skin Tone",
  "keywords": [
    "pinch",
    "small",
    "amount",
    "little",
    "hand",
    "medium dark skin tone"
  ],
  "category": "People & Body",
  "alsoKnownAs": [
    "Small Amount",
    "Just a Little"
  ],
  "version": {
    "unicode-version": "12.0",
    "emoji-version": "12.0"
  },
  "description": "A hand with the thumb and index finger pinched together, often used to indicate a small amount, a precise measurement, or a subtle gesture. The medium-dark skin tone specifies the skin color.",
  "apple_vendor_description": "The pinching hand emoji on Apple devices, rendered in a medium-dark skin tone, displays a precise and deliberate gesture with its thumb and index finger brought close together. Apple's characteristic soft rounded edges and realistic lighting make the skin texture appear natural and the hand’s form subtly three-dimensional. This emoji often conveys a sense of 'just a little bit,' a subtle emphasis, or even a sarcastic 'you don't say?' in Apple-centric digital communication."
}