{
  "generated": true,
  "code": "🫶🏿",
  "Unicode": [
    "U+1F90F",
    "U+1F3FF"
  ],
  "slug": "love-you-gesture-dark-skin-tone",
  "shortcodes": {
    "github": ":heart_hands_dark_skin_tone:",
    "slack": ":love_you_gesture_dark_skin_tone:",
    "discord": ":love_you_gesture_dark_skin_tone:"
  },
  "title": "Love You Gesture Dark Skin Tone",
  "keywords": [
    "love",
    "heart",
    "gesture",
    "affection",
    "dark skin tone"
  ],
  "category": "People & Body",
  "alsoKnownAs": [
    "I love you gesture",
    "heart hands dark skin tone"
  ],
  "version": {
    "unicode-version": "13.0",
    "emoji-version": "13.0"
  },
  "description": "A hand gesture forming a heart shape, with a dark skin tone. It signifies love, affection, or sending positive vibes.",
  "apple_vendor_description": "The 'I Love You' gesture emoji on Apple devices is a dynamic and expressive hand, rendered in a rich dark skin tone with Apple's signature glossy 3D shading.  Its smooth, rounded fingers are elegantly curled to form the iconic sign, catching light with a realistic gleam that imbues it with warmth and sincerity.  This universally recognized symbol, perfectly realized with Apple's visual flair, conveys deep affection, heartfelt sentiment, and loving appreciation in digital communication."
}