{
  "code": "🫄",
  "Unicode": [
    "U+1FAC4"
  ],
  "slug": "pregnant-person",
  "shortcodes": {
    "discord": ":pregnant_person:",
    "slack": ":pregnant_person:"
  },
  "title": "Pregnant Person",
  "keywords": [
    "belly",
    "bloated",
    "full",
    "pregnant",
    "pregnant person"
  ],
  "category": "People & Body",
  "alsoKnownAs": [],
  "version": {
    "unicode-version": "14.0",
    "emoji-version": "14.0"
  },
  "description": "<p>A pregnant person holding their round stomach. Sometimes used in jest to represent feeling too full after overeating, as in a &quot;food baby.&quot;</p>\r\n\r\n<p>Variants include <a href=\"/pregnant-woman/\">🫄 Pregnant Woman</a> and <a href=\"/pregnant-man/\">🫃 Pregnant Man</a>.</p>\r\n\r\n<p>This emoji was approved to make the emoji keyboard more <a href=\"https://blog.emojipedia.org/why-is-there-a-pregnant-man-emoji/\">consistent and gender inclusive</a>.</p>",
  "apple_vendor_description": "The pregnant person emoji on Apple devices is depicted with graceful curves and a subtly rounded belly, rendered in Apple's signature smooth gradients and soft rounded edges that convey a sense of gentle anticipation. Realistic lighting accentuates the form, giving it a warm and comforting presence. This emoji, with its serene expression, symbolizes new beginnings, family growth, and the profound journey of pregnancy, offering a sensitive and respectful representation in digital conversations."
}