{
  "generated": true,
  "code": "🤰🏿",
  "Unicode": [
    "U+1F930",
    "U+1F3FF"
  ],
  "slug": "pregnant-person-medium-dark-skin-tone",
  "shortcodes": {
    "github": ":pregnant_medium_dark_skin_tone:",
    "slack": ":pregnant_medium_dark_skin_tone:",
    "discord": ":pregnant_medium_dark_skin_tone:"
  },
  "title": "Pregnant Person Medium Dark Skin Tone",
  "keywords": [
    "pregnant",
    "pregnancy",
    "baby",
    "expecting",
    "mother",
    "person",
    "medium dark skin tone"
  ],
  "category": "People & Body",
  "alsoKnownAs": [],
  "version": {
    "unicode-version": "10.0",
    "emoji-version": "5.0"
  },
  "description": "Represents a person who is pregnant, with a medium dark skin tone. It signifies anticipation, new life, and the journey of pregnancy.",
  "apple_vendor_description": "On Apple devices, the pregnant person emoji with a medium-dark skin tone shows a gentle silhouette, conveying a profound sense of anticipation and new beginnings. Apple's design language imbues this emoji with soft, rounded forms and realistic lighting that highlight the subtle curve of the belly, symbolizing fertility, growth, and the journey of parenthood. It’s a respectful and tender representation used to share news of pregnancy or express support for expectant individuals."
}